LICENSE
README.md
setup.cfg
setup.py
brix/__init__.py
brix/classes.py
brix/functions.py
brix/grid_maker.py
brix/helpers.py
brix/test_tools.py
brix/examples/__init__.py
brix/examples/examples.py
cs_brix.egg-info/PKG-INFO
cs_brix.egg-info/SOURCES.txt
cs_brix.egg-info/dependency_links.txt
cs_brix.egg-info/requires.txt
cs_brix.egg-info/top_level.txt
test/test_api.py
test/test_classes.py
test/test_tables.py