Metadata-Version: 2.1
Name: cs-brix
Version: 0.0.10
Summary: Brix is a python library for CityScope modules which handles communication with City I/O.
Home-page: https://github.com/CityScope/CS_Brix
Author: CityScience MIT
Author-email: csadmin@media.mit.edu
License: GNU General Public License v3.0 only (GPL-3.0-only)
Download-URL: https://github.com/CityScope/CS_Brix/archive/v_0.0.10.tar.gz
Platform: UNKNOWN
Classifier: Development Status :: 3 - Alpha
Classifier: Intended Audience :: Developers
Classifier: License :: OSI Approved :: GNU General Public License v3 (GPLv3)
Classifier: Programming Language :: Python :: 3.6
Classifier: Programming Language :: Python :: 3.7
Classifier: Operating System :: OS Independent
Requires-Python: >=3.6
